[
  {
    "eventType": "DELAYED_MESSAGE_POSTED",
    "timestamp": 1533451522399,
    "actionCode": -1,
    "delayTime": 3598465,
    "canScrollTo": false,
    "elementDescriptors": []
  },
  {
    "eventType": "VIEW_CLICKED",
    "timestamp": 1533451532341,
    "replacementText": "Sign in with Facebook",
    "actionCode": -1,
    "delayTime": 0,
    "canScrollTo": true,
    "elementDescriptors": [
      {
        "className": "com.firebase.ui.auth.util.ui.SupportVectorDrawablesButton",
        "recyclerViewChildPosition": -1,
        "adapterViewChildPosition": -1,
        "groupViewChildPosition": 1,
        "resourceId": "com.gz.jey.go4lunch:id/facebook_button",
        "contentDescription": "",
        "text": "Sign in with Facebook"
      },
      {
        "className": "android.widget.LinearLayout",
        "recyclerViewChildPosition": -1,
        "adapterViewChildPosition": -1,
        "groupViewChildPosition": 0,
        "resourceId": "com.gz.jey.go4lunch:id/btn_holder",
        "contentDescription": "",
        "text": ""
      },
      {
        "className": "android.widget.ScrollView",
        "recyclerViewChildPosition": -1,
        "adapterViewChildPosition": -1,
        "groupViewChildPosition": 2,
        "resourceId": "com.gz.jey.go4lunch:id/container",
        "contentDescription": "",
        "text": ""
      }
    ]
  },
  {
    "eventType": "DELAYED_MESSAGE_POSTED",
    "timestamp": 1533451534442,
    "actionCode": -1,
    "delayTime": 3589981,
    "canScrollTo": false,
    "elementDescriptors": []
  },
  {
    "eventType": "PRESSED_BACK",
    "timestamp": 1533451561699,
    "actionCode": -1,
    "delayTime": 0,
    "canScrollTo": false,
    "elementDescriptors": []
  },
  {
    "eventType": "DELAYED_MESSAGE_POSTED",
    "timestamp": 1533451571446,
    "actionCode": -1,
    "delayTime": 3598240,
    "canScrollTo": false,
    "elementDescriptors": []
  }
]